{"target": -0.34184387397832616, "params": {"poly_debase": 1.0, "polyorder": 2.0, "prominence": 100000.0, "width": 10.0, "window": 16.931584271345898}, "datetime": {"datetime": "2019-02-01 00:37:16", "elapsed": 0.0, "delta": 0.0}}
{"target": -0.5369382309366907, "params": {"poly_debase": 1.0, "polyorder": 2.0, "prominence": 100000.0, "width": 10.0, "window": 290.76596096569835}, "datetime": {"datetime": "2019-02-01 00:37:16", "elapsed": 0.417589, "delta": 0.417589}}
{"target": -0.48721114076888233, "params": {"poly_debase": 1.0, "polyorder": 2.0, "prominence": 100000.0, "width": 10.0, "window": 239.812347134982}, "datetime": {"datetime": "2019-02-01 00:37:17", "elapsed": 0.871762, "delta": 0.454173}}
{"target": -0.4746007816119854, "params": {"poly_debase": 1.0, "polyorder": 2.0, "prominence": 100000.0, "width": 10.0, "window": 197.45254213787055}, "datetime": {"datetime": "2019-02-01 00:37:17", "elapsed": 1.396269, "delta": 0.524507}}
{"target": -0.3937095913498275, "params": {"poly_debase": 1.0, "polyorder": 2.0, "prominence": 100000.0, "width": 10.0, "window": 137.59994126864024}, "datetime": {"datetime": "2019-02-01 00:37:18", "elapsed": 2.108249, "delta": 0.71198}}
{"target": -0.7421741285486052, "params": {"poly_debase": 1.0, "polyorder": 2.0, "prominence": 100000.0, "width": 10.0, "window": 500.0}, "datetime": {"datetime": "2019-02-01 00:37:24", "elapsed": 8.281, "delta": 6.172751}}
{"target": -0.4206885487279064, "params": {"poly_debase": 1.0, "polyorder": 2.0, "prominence": 100000.0, "width": 10.0, "window": 64.7241565229016}, "datetime": {"datetime": "2019-02-01 00:37:34", "elapsed": 17.793143, "delta": 9.512143}}
{"target": -0.35751614216741207, "params": {"poly_debase": 1.0, "polyorder": 2.0, "prominence": 100000.0, "width": 10.0, "window": 10.0}, "datetime": {"datetime": "2019-02-01 00:37:45", "elapsed": 28.894909, "delta": 11.101766}}
{"target": -0.49888379461343035, "params": {"poly_debase": 1.0, "polyorder": 2.0, "prominence": 100000.0, "width": 10.0, "window": 403.6740909338187}, "datetime": {"datetime": "2019-02-01 00:37:52", "elapsed": 36.046484, "delta": 7.151575}}
{"target": -0.46428797423187484, "params": {"poly_debase": 1.0, "polyorder": 2.0, "prominence": 100000.0, "width": 10.0, "window": 357.48688971575154}, "datetime": {"datetime": "2019-02-01 00:38:01", "elapsed": 44.809974, "delta": 8.76349}}
{"target": -0.3373901232910601, "params": {"poly_debase": 1.0, "polyorder": 2.0, "prominence": 100000.0, "width": 10.0, "window": 30.618175721341068}, "datetime": {"datetime": "2019-02-01 00:38:11", "elapsed": 54.991469, "delta": 10.181495}}
{"target": -0.34661799802393345, "params": {"poly_debase": 1.0, "polyorder": 2.0, "prominence": 100000.0, "width": 10.0, "window": 25.753447613586587}, "datetime": {"datetime": "2019-02-01 00:38:21", "elapsed": 65.258485, "delta": 10.267016}}
{"target": -0.3626310851205288, "params": {"poly_debase": 1.0, "polyorder": 2.0, "prominence": 100000.0, "width": 10.0, "window": 25.66811699071476}, "datetime": {"datetime": "2019-02-01 00:38:32", "elapsed": 76.157767, "delta": 10.899282}}
{"target": -0.6836510295638402, "params": {"poly_debase": 1.0, "polyorder": 2.0, "prominence": 100000.0, "width": 10.0, "window": 451.47831237382803}, "datetime": {"datetime": "2019-02-01 00:38:38", "elapsed": 82.708185, "delta": 6.550418}}
{"target": -0.40206269150264357, "params": {"poly_debase": 1.0, "polyorder": 2.0, "prominence": 100000.0, "width": 10.0, "window": 164.7573310809926}, "datetime": {"datetime": "2019-02-01 00:38:45", "elapsed": 89.71807, "delta": 7.009885}}
{"target": -0.38154088963180166, "params": {"poly_debase": 1.0, "polyorder": 2.0, "prominence": 100000.0, "width": 10.0, "window": 34.331264736075475}, "datetime": {"datetime": "2019-02-01 00:38:56", "elapsed": 99.802581, "delta": 10.084511}}
{"target": -0.3124134236200934, "params": {"poly_debase": 1.0, "polyorder": 2.0, "prominence": 100000.0, "width": 10.0, "window": 100.39511975208202}, "datetime": {"datetime": "2019-02-01 00:39:01", "elapsed": 105.251609, "delta": 5.449028}}
{"target": -0.5810512783295233, "params": {"poly_debase": 1.0, "polyorder": 2.0, "prominence": 100000.0, "width": 10.0, "window": 324.5020610758273}, "datetime": {"datetime": "2019-02-01 00:39:06", "elapsed": 110.007306, "delta": 4.755697}}
{"target": -0.4346709928596591, "params": {"poly_debase": 1.0, "polyorder": 2.0, "prominence": 100000.0, "width": 10.0, "window": 264.7441134556909}, "datetime": {"datetime": "2019-02-01 00:39:11", "elapsed": 115.336536, "delta": 5.32923}}
{"target": -0.4562306427249685, "params": {"poly_debase": 1.0, "polyorder": 2.0, "prominence": 100000.0, "width": 10.0, "window": 380.8281354439212}, "datetime": {"datetime": "2019-02-01 00:39:16", "elapsed": 120.202403, "delta": 4.865867}}
{"target": -0.3870404180777809, "params": {"poly_debase": 1.0, "polyorder": 2.0, "prominence": 100000.0, "width": 10.0, "window": 83.46104348642184}, "datetime": {"datetime": "2019-02-01 00:39:22", "elapsed": 125.851621, "delta": 5.649218}}
{"target": -0.45614867353228467, "params": {"poly_debase": 1.0, "polyorder": 2.0, "prominence": 100000.0, "width": 10.0, "window": 427.59356274952944}, "datetime": {"datetime": "2019-02-01 00:39:27", "elapsed": 131.006675, "delta": 5.155054}}
{"target": -0.39501280615797246, "params": {"poly_debase": 1.0, "polyorder": 2.0, "prominence": 100000.0, "width": 10.0, "window": 118.59243183608108}, "datetime": {"datetime": "2019-02-01 00:39:33", "elapsed": 137.172942, "delta": 6.166267}}
{"target": -0.5041642176143377, "params": {"poly_debase": 1.0, "polyorder": 2.0, "prominence": 100000.0, "width": 10.0, "window": 217.9652373468815}, "datetime": {"datetime": "2019-02-01 00:39:39", "elapsed": 143.185991, "delta": 6.013049}}
{"target": -0.7301038680743135, "params": {"poly_debase": 1.0, "polyorder": 2.0, "prominence": 100000.0, "width": 10.0, "window": 477.85475653925243}, "datetime": {"datetime": "2019-02-01 00:39:45", "elapsed": 149.583868, "delta": 6.397877}}
{"target": -0.42117994527921965, "params": {"poly_debase": 1.0, "polyorder": 2.0, "prominence": 100000.0, "width": 10.0, "window": 179.9393367038903}, "datetime": {"datetime": "2019-02-01 00:39:53", "elapsed": 156.738487, "delta": 7.154619}}
{"target": -0.3811851843579994, "params": {"poly_debase": 1.0, "polyorder": 2.0, "prominence": 100000.0, "width": 10.0, "window": 150.61936741436776}, "datetime": {"datetime": "2019-02-01 00:40:00", "elapsed": 164.11662, "delta": 7.378133}}
{"target": -0.4777497802268716, "params": {"poly_debase": 1.0, "polyorder": 2.0, "prominence": 100000.0, "width": 10.0, "window": 342.0937349856466}, "datetime": {"datetime": "2019-02-01 00:40:08", "elapsed": 172.135704, "delta": 8.019084}}
{"target": -0.35588819653734255, "params": {"poly_debase": 1.0, "polyorder": 2.0, "prominence": 100000.0, "width": 10.0, "window": 107.14871001229896}, "datetime": {"datetime": "2019-02-01 00:40:17", "elapsed": 181.476506, "delta": 9.340802}}
{"target": -0.3116931846497294, "params": {"poly_debase": 1.0, "polyorder": 2.0, "prominence": 100000.0, "width": 10.0, "window": 93.95526444324871}, "datetime": {"datetime": "2019-02-01 00:40:26", "elapsed": 190.696674, "delta": 9.220168}}
{"target": -0.3457959849913296, "params": {"poly_debase": 1.0, "polyorder": 2.0, "prominence": 100000.0, "width": 10.0, "window": 97.11685216001834}, "datetime": {"datetime": "2019-02-01 00:40:36", "elapsed": 200.590467, "delta": 9.893793}}
{"target": -0.6268734244203259, "params": {"poly_debase": 1.0, "polyorder": 2.0, "prominence": 100000.0, "width": 10.0, "window": 306.7696898291952}, "datetime": {"datetime": "2019-02-01 00:40:42", "elapsed": 206.282122, "delta": 5.691655}}
{"target": -0.5278406177492024, "params": {"poly_debase": 1.0, "polyorder": 2.0, "prominence": 100000.0, "width": 10.0, "window": 276.7405699238381}, "datetime": {"datetime": "2019-02-01 00:40:48", "elapsed": 212.413354, "delta": 6.131232}}
{"target": -0.4474473924849136, "params": {"poly_debase": 1.0, "polyorder": 2.0, "prominence": 100000.0, "width": 10.0, "window": 252.27570674897802}, "datetime": {"datetime": "2019-02-01 00:40:55", "elapsed": 219.492834, "delta": 7.07948}}
{"target": -0.405057906648973, "params": {"poly_debase": 1.0, "polyorder": 2.0, "prominence": 100000.0, "width": 10.0, "window": 52.7119991713645}, "datetime": {"datetime": "2019-02-01 00:41:03", "elapsed": 227.540545, "delta": 8.047711}}
